quri_sdk/_quri_sdk_meta.py
quri_sdk-0.24.1.dist-info/METADATA
quri_sdk-0.24.1.dist-info/WHEEL
quri_sdk-0.24.1.dist-info/RECORD
